flowsynth/__init__.py
flowsynth/__main__.py
flowsynth/flowsynth.py
flowsynth-1.4.1.data/scripts/flowsynth.py
flowsynth-1.4.1.dist-info/LICENSE
flowsynth-1.4.1.dist-info/METADATA
flowsynth-1.4.1.dist-info/WHEEL
flowsynth-1.4.1.dist-info/top_level.txt
flowsynth-1.4.1.dist-info/RECORD
