Metadata-Version: 2.1
Name: flowsynth
Version: 1.4.1
Summary: Flowsynth is a tool for rapidly modeling network traffic. Flowsynth can be used to generate text-based hexdumps of packets as well as native libpcap format packet captures.
Home-page: https://github.com/secureworks/flowsynth
Author: Will Urbanski
Maintainer: David Wharton
Maintainer-email: whartond@users.noreply.github.com
License: UNKNOWN
Project-URL: Documentation, https://github.com/secureworks/flowsynth/blob/master/README.md
Project-URL: Source, https://github.com/secureworks/flowsynth
Keywords: pcap,pcaps,packet capture,libpcap,IDS,IPS,packets,scapy
Platform: UNKNOWN
Classifier: Development Status :: 5 - Production/Stable
Classifier: Programming Language :: Python :: 2.7
Classifier: Programming Language :: Python :: 3
Classifier: License :: OSI Approved :: Apache Software License
Classifier: Operating System :: OS Independent
Classifier: Intended Audience :: Information Technology
Classifier: Intended Audience :: Developers
Classifier: Topic :: System :: Networking
Requires-Python: >=2.7
Requires-Dist: scapy (>=2.4.0)
Requires-Dist: argparse
